fractal_server/__init__.py
fractal_server/__main__.py
fractal_server/alembic.ini
fractal_server/app/__init__.py
fractal_server/app/db/__init__.py
fractal_server/app/models/__init__.py
fractal_server/app/models/linkusergroup.py
fractal_server/app/models/linkuserproject.py
fractal_server/app/models/security.py
fractal_server/app/models/v2/__init__.py
fractal_server/app/models/v2/accounting.py
fractal_server/app/models/v2/dataset.py
fractal_server/app/models/v2/history.py
fractal_server/app/models/v2/job.py
fractal_server/app/models/v2/profile.py
fractal_server/app/models/v2/project.py
fractal_server/app/models/v2/resource.py
fractal_server/app/models/v2/task.py
fractal_server/app/models/v2/task_group.py
fractal_server/app/models/v2/workflow.py
fractal_server/app/models/v2/workflowtask.py
fractal_server/app/routes/__init__.py
fractal_server/app/routes/admin/__init__.py
fractal_server/app/routes/admin/v2/__init__.py
fractal_server/app/routes/admin/v2/_aux_functions.py
fractal_server/app/routes/admin/v2/accounting.py
fractal_server/app/routes/admin/v2/impersonate.py
fractal_server/app/routes/admin/v2/job.py
fractal_server/app/routes/admin/v2/profile.py
fractal_server/app/routes/admin/v2/resource.py
fractal_server/app/routes/admin/v2/sharing.py
fractal_server/app/routes/admin/v2/task.py
fractal_server/app/routes/admin/v2/task_group.py
fractal_server/app/routes/admin/v2/task_group_lifecycle.py
fractal_server/app/routes/api/__init__.py
fractal_server/app/routes/api/alive.py
fractal_server/app/routes/api/settings.py
fractal_server/app/routes/api/v2/__init__.py
fractal_server/app/routes/api/v2/_aux_functions.py
fractal_server/app/routes/api/v2/_aux_functions_history.py
fractal_server/app/routes/api/v2/_aux_functions_sharing.py
fractal_server/app/routes/api/v2/_aux_functions_task_lifecycle.py
fractal_server/app/routes/api/v2/_aux_functions_task_version_update.py
fractal_server/app/routes/api/v2/_aux_functions_tasks.py
fractal_server-2.19.0.dist-info/licenses/LICENSE
fractal_server-2.19.0.dist-info/WHEEL
fractal_server-2.19.0.dist-info/entry_points.txt
fractal_server-2.19.0.dist-info/METADATA
fractal_server-2.19.0.dist-info/RECORD
