Metadata-Version: 2.4
Name: fractal-server
Version: 2.19.0
Summary: Backend component of the Fractal analytics platform
Author: Tommaso Comparin, Marco Franzon, Yuri Chiucconi, Jacopo Nespolo
Author-email: Tommaso Comparin <tommaso.comparin@exact-lab.it>, Marco Franzon <marco.franzon@exact-lab.it>, Yuri Chiucconi <yuri.chiucconi@exact-lab.it>, Jacopo Nespolo <jacopo.nespolo@exact-lab.it>
License-Expression: BSD-3-Clause
License-File: LICENSE
Requires-Dist: fastapi>=0.128.0,<0.129.0
Requires-Dist: sqlmodel==0.0.31
Requires-Dist: sqlalchemy[asyncio]>=2.0.23,<2.1
Requires-Dist: fastapi-users[oauth]>=15,<16
Requires-Dist: alembic>=1.13.1,<2.0.0
Requires-Dist: uvicorn>=0.40.0,<0.41.0
Requires-Dist: uvicorn-worker==0.4.0
Requires-Dist: pydantic>=2.12.0,<2.13.0
Requires-Dist: pydantic-settings==2.12.0
Requires-Dist: packaging>=25.0.0,<26.0.0
Requires-Dist: fabric>=3.2.2,<3.3.0
Requires-Dist: gunicorn>=24.1,<25
Requires-Dist: psycopg[binary]>=3.1.0,<4.0.0
Requires-Dist: tomli-w>=1.2.0,<1.3.0
Requires-Python: >=3.12, <3.15
Project-URL: changelog, https://github.com/fractal-analytics-platform/fractal-server/blob/main/CHANGELOG.md
Project-URL: documentation, https://fractal-analytics-platform.github.io/fractal-server
Project-URL: homepage, https://github.com/fractal-analytics-platform/fractal-server
Project-URL: repository, https://github.com/fractal-analytics-platform/fractal-server
